bg_remover/__init__.py
bg_remover/remover.py
bg_remover_lk-1.0.dist-info/METADATA
bg_remover_lk-1.0.dist-info/WHEEL
bg_remover_lk-1.0.dist-info/top_level.txt
bg_remover_lk-1.0.dist-info/RECORD
