Metadata-Version: 2.1
Name: bg-remover-lk
Version: 1.0
Requires-Dist: rembg
Requires-Dist: Pillow
